rsk/__init__.py
rsk/rsk.py
rsk-0.1.3.dist-info/LICENSE
rsk-0.1.3.dist-info/METADATA
rsk-0.1.3.dist-info/WHEEL
rsk-0.1.3.dist-info/top_level.txt
rsk-0.1.3.dist-info/RECORD
